Workbook

Sheet 1. Overview
A1: PROJECT NEXUS — PRODUCT COMPLETION PLAN (Release 1)
A2: Source: SRS Nexus E-Commerce & Auction v1.0 (04/06/2026, HauNK) · Prepared by: Tuan Nghiem · Date: 22/09/2026
A4: A. CAPACITY MATH — WHY 6 MONTHS ISN'T ENOUGH
A5: Metric | B5: Value | C5: Unit | E5: Calculation / Notes
A6: Total SRS v1.0 scope (full) | B6: =B7+B9 -> 816 | C6: dev-day | E6: All of SRS sections 3, 4, 5 at production depth — EXCLUDES tech-stack training
A7: • SRS features | B7: 609 | C7: dev-day | E7: Sheet “2. Backlog” — total of the Estimate column, minus the 3 training tasks
A8: • Tech-stack training (sprint S0) | B8: 44 | C8: dev-day | E8: Sheet “2. Backlog” — F01.0a/b/c, not part of SRS scope
A9: • Deferred to R1.1 / R2 | B9: 207 | C9: dev-day | E9: Sheet “6. Deferred” — each item has a reason
A10: Release 1 scope (SRS features + training) | B10: =B7+B8 -> 653 | C10: dev-day | E10: Actual scope the team must deliver over 17 sprints (S0–S16)
A11: Proposed team | B11: 8 | C11: people | E11: 1 PO/PM, 1 Tech Lead, 4 Backend, 1 Frontend, 1 QA (sheet 8)
A12: Effective dev capacity | B12: 5.5 | C12: FTE | E12: Tech Lead 50% + 4 Backend + 1 Frontend. PO/PM and QA aren't counted in dev capacity
A13: Output per FTE per sprint | B13: 8 | C13: dev-day | E13: 10 working days x 80% (ceremonies, code review, support, bug fixes)
A14: Dev capacity per sprint | B14: =B12*B13 -> 44 | C14: dev-day | E14: 5.5 FTE x 8 dev-day
A15: Sprints needed for R1 scope | B15: =ROUND(B10/B14,1) -> 14.8 | C15: sprint | E15: Not counting the inception sprint or the hardening sprint
A16: If holding the 6-month target (10 effective sprints) | B16: =ROUND(B10/10/B13,1) -> 8.2 | C16: FTE | E16: Dev FTE NEEDED to finish R1 scope in 10 effective sprints (after subtracting Christmas/Tet + training)
A17: CONCLUSION | B17: =CONCATENATE("R1 scope needs ",ROUND(B10/B14,1)," sprints of dev work. To finish in 10 effective sprints (6 months, after subtracting Christmas/Tet + training) requires ",ROUND(B10/10/B13,1)," dev FTE, i.e. a team of about 11 (Option A). Keeping an 8-person team needs 17 sprints = 8.4 months.") -> R1 scope needs 14.8 sprints of dev work. To finish in 10 effective sprints (6 months, after subtracting Christmas/Tet + training) requires 8.2 dev FTE, i.e. a team of about 11 (Option A). Keeping an 8-person team needs 17 sprints = 8.4 months.
A20: B. THREE OPTIONS — DECISION NEEDED BEFORE 30/09/2026
A21: Option | B21: Team | C21: Go-live | D21: Duration | E21: Pros / Cons
A22: A. Hold the 6-month date - add headcount | B22: 11 people (1 PM, 1 TL, 7 BE, 1 FE, 1 QA) | C22: 16/04/2027 | D22: 6.6 months | E22: (+) Nearly hits the 6-month mark; keeps full scope (-) Cost rises about 37%; onboarding 3 new devs into a greenfield project (Brooks' law); hiring must close before 30/09/2026; should hire people who already know Java/Spring Boot to avoid extending the training sprint Scope: Full Must-scope (653 dev-day, including 44d tech-stack training)
A23: B. Keep the 8-person team - extend the timeline (RECOMMENDED) | B23: 8 people (1 PM, 1 TL, 4 BE, 1 FE, 1 QA) | C23: 12/06/2027 | D23: 8.4 months | E23: (+) Lowest cost; small, stable team, low communication overhead (-) 2 months later than the original target Scope: Full Must-scope (653 dev-day, including 44d tech-stack training)
A24: C. Hold the 6-month date - cut auction | B24: 8 people | C24: 30/04/2027 | D24: 7.0 months | E24: (+) Nearly hits the date, no added cost (-) Loses the product's key differentiator; auction is the whole reason Project Nexus exists Scope: E-commerce only (518 dev-day, including 44d tech-stack training). Auction moves to R2, Q4 2027
A27: C. KEY ASSUMPTIONS (if any of these is wrong, the plan must be redone)
A28: • ADR-002: use a MODULAR MONOLITH (bounded contexts + separate schemas + event bus) for 6 domains, with the Auction Service SPLIT OUT separately. 7 microservices with 5 devs is an anti-pattern; this assumption saves roughly 60 dev-day of platform and operational work.
A29: • Frontend has NO custom design: admin and seller portal use a ready-made template (Ant Design Pro / Refine), the buyer web uses Tailwind with a component library. The 101 dev-day frontend estimate is only sufficient at this level.
A30: • Only 1 payment gateway (Stripe) and 1 carrier (GHN) are integrated in R1. The adapter framework is ready to add more carriers later.
A31: • PostgreSQL Full-Text Search is sufficient to meet the <= 800ms search SLA up to about 500,000 products. OpenSearch is deferred to R1.1.
A32: • SRS v1.1 (adding System Context, Architecture, Component diagrams and a promotions spec) is completed before S3 = 20/11/2026.
A33: • 1 dev-day is 1 EFFECTIVE working day (after subtracting 20% for ceremonies, support, review) — not 1 calendar day.
A34: • The actual dev buffer is only 3.8% (Track B) to 11.5% (Track A) — LOW versus the 20-25% standard for a greenfield project. As a result: the target go-live is 12/06/2027, and the externally COMMITTED go-live is 26/06/2027 (adding 1 contingency sprint).

Sheet 2. Backlog
A1: Feature ID | B1: Epic | C1: Epic Name | D1: Feature Name | E1: SRS ref | F1: Priority | G1: Estimate (dev-day) | H1: Track | I1: Sprint | J1: Dependencies | K1: Definition of Done
A2: F01.0a | B2: E01 | C2: Platform Foundation | D2: Tech stack training - Backend: Java, Spring Boot (Tech Lead + Backend Track A) | E2: - | F2: Must | G2: 20 | H2: A | I2: S0 | J2: - | K2: Complete the Java + Spring Boot training/hands-on course; build 1 sample CRUD service with unit tests and DB connectivity
A3: F01.0b | B3: E01 | C3: Platform Foundation | D3: Tech stack training - Backend: Java, Spring Boot (Backend Track B) | E3: - | F3: Must | G3: 16 | H3: B | I3: S0 | J3: - | K3: Complete the same training/hands-on course as Track A
A4: F01.0c | B4: E01 | C4: Platform Foundation | D4: Tech stack training - Frontend: ReactJS, HTML, CSS | E4: - | F4: Must | G4: 8 | H4: FE | I4: S0 | J4: - | K4: Build 1 sample page with components, state, API calls, responsive HTML/CSS
A5: F01.1 | B5: E01 | C5: Platform Foundation | D5: Finalize tech stack + ADRs + repository structure | E5: 4.1 | F5: Must | G5: 3 | H5: A | I5: S1 | J5: - | K5: ADR-001..005 signed off by Tech Lead and PO
A6: F01.2 | B6: E01 | C6: Platform Foundation | D6: Service/module template (clean architecture, DDD, health checks, config) | E6: 4.1 | F6: Must | G6: 5 | H6: A | I6: S1 | J6: F01.1 | K6: Scaffold a new module in under 1 hour
A7: F01.5 | B7: E01 | C7: Platform Foundation | D7: CI/CD: build, test, SAST, container scanning, rolling deploy | E7: 5.7 | F7: Must | G7: 8 | H7: A | I7: S1 | J7: F01.1 | K7: Commit to STAGING in under 15 minutes, zero downtime
A8: F01.3 | B8: E01 | C8: Platform Foundation | D8: API Gateway: routing, rate limiting, JWT validation | E8: 5.4 | F8: Must | G8: 5 | H8: A | I8: S2 | J8: F01.2 | K8: Requests through the gateway carry a trace-id
A9: F01.4 | B9: E01 | C9: Platform Foundation | D9: Event bus (Kafka) + schema registry + Outbox library | E9: 2.8 | F9: Must | G9: 9 | H9: A | I9: S2 | J9: F01.2 | K9: Publish/consume 1 real event, at-least-once with dedup
A10: F01.6 | B10: E01 | C10: Platform Foundation | D10: DEV/STAGING environments on K8s + secret management | E10: 4.3 | F10: Must | G10: 5 | H10: A | I10: S2 | J10: F01.5 | K10: No secrets remain in source code
A11: F13.1 | B11: E13 | C11: Web Frontend (Buyer / Seller / Admin) | D11: Design system + component library + responsive framework | E11: - | F11: Must | G11: 12 | H11: FE | I11: S2–S3 | J11: F01.3 | K11: Storybook; 20 base components
A12: F01.7 | B12: E01 | C12: Platform Foundation | D12: Observability: OpenTelemetry, Prometheus, Grafana, centralized logging | E12: 5.5 | F12: Must | G12: 4 | H12: A | I12: S3 | J12: F01.6 | K12: Trace spans gateway to service to DB; p95/p99 dashboard
A13: F01.8 | B13: E01 | C13: Platform Foundation | D13: Shared library: idempotency, correlation-id, error contract, OpenAPI generation | E13: 4.2 | F13: Must | G13: 3 | H13: A | I13: S3 | J13: F01.2 | K13: OpenAPI spec generated from code and auto-published
... A85: F14.5 | B85: E14 | C85: Quality & NFR Compliance | D85: DR drill: backup/restore, RTO 4h / RPO 15 min | E85: 5.7 | F85: Must | G85: 3 | H85: QA | I85: S16 | J85: F01.6 | K85: Successful restore with evidence
D86: TOTAL RELEASE 1 SCOPE | G86: =SUM(G2:G85) -> 653

Sheet 3. Epic Summary
A1: SUMMARY BY EPIC
A4: Epic | B4: Epic Name | C4: Service / Domain | D4: Track | E4: Features | F4: Estimate (dev-day) | G4: % of total scope | H4: Start sprint | I4: End sprint
A5: E01 | B5: Platform Foundation | C5: Cross-cutting | D5: A | E5: =COUNTIF('2. Backlog'!$B$2:$B$85,A5) -> 11 | F5: =SUMIFS('2. Backlog'!$G$2:$G$85,'2. Backlog'!$B$2:$B$85,A5) -> 86 | G5: =F5/$F$19 -> 0.13169985 | H5: S0 | I5: S3
A6: E02 | B6: User Service - Identity & Access | C6: User Service | D6: A | E6: =COUNTIF('2. Backlog'!$B$2:$B$85,A6) -> 6 | F6: =SUMIFS('2. Backlog'!$G$2:$G$85,'2. Backlog'!$B$2:$B$85,A6) -> 39 | G6: =F6/$F$19 -> 0.059724349 | H6: S3 | I6: S5
A7: E03 | B7: Notification Service | C7: Notification Service | D7: B | E7: =COUNTIF('2. Backlog'!$B$2:$B$85,A7) -> 4 | F7: =SUMIFS('2. Backlog'!$G$2:$G$85,'2. Backlog'!$B$2:$B$85,A7) -> 22 | G7: =F7/$F$19 -> 0.033690658 | H7: S3 | I7: S4
A8: E04 | B8: Catalog Service | C8: Catalog Service | D8: A | E8: =COUNTIF('2. Backlog'!$B$2:$B$85,A8) -> 5 | F8: =SUMIFS('2. Backlog'!$G$2:$G$85,'2. Backlog'!$B$2:$B$85,A8) -> 30 | G8: =F8/$F$19 -> 0.045941807 | H8: S5 | I8: S7
A9: E05 | B9: Commerce - Cart, Checkout, Payment | C9: Commerce Service | D9: A | E9: =COUNTIF('2. Backlog'!$B$2:$B$85,A9) -> 7 | F9: =SUMIFS('2. Backlog'!$G$2:$G$85,'2. Backlog'!$B$2:$B$85,A9) -> 73 | G9: =F9/$F$19 -> 0.11179173 | H9: S7 | I9: S11
A10: E06 | B10: Commerce - Order Management | C10: Commerce Service | D10: A | E10: =COUNTIF('2. Backlog'!$B$2:$B$85,A10) -> 6 | F10: =SUMIFS('2. Backlog'!$G$2:$G$85,'2. Backlog'!$B$2:$B$85,A10) -> 49 | G10: =F10/$F$19 -> 0.075038285 | H10: S11 | I10: S15
A11: E07 | B11: Auction - Session Management | C11: Auction Service | D11: B | E11: =COUNTIF('2. Backlog'!$B$2:$B$85,A11) -> 5 | F11: =SUMIFS('2. Backlog'!$G$2:$G$85,'2. Backlog'!$B$2:$B$85,A11) -> 34 | G11: =F11/$F$19 -> 0.052067381 | H11: S6 | I11: S9
A12: E08 | B12: Auction - Bidding | C12: Auction Service | D12: B | E12: =COUNTIF('2. Backlog'!$B$2:$B$85,A12) -> 6 | F12: =SUMIFS('2. Backlog'!$G$2:$G$85,'2. Backlog'!$B$2:$B$85,A12) -> 48 | G12: =F12/$F$19 -> 0.073506891 | H12: S9 | I12: S12
A13: E09 | B13: Auction - Settlement | C13: Auction Service | D13: B | E13: =COUNTIF('2. Backlog'!$B$2:$B$85,A13) -> 5 | F13: =SUMIFS('2. Backlog'!$G$2:$G$85,'2. Backlog'!$B$2:$B$85,A13) -> 36 | G13: =F13/$F$19 -> 0.055130168 | H13: S12 | I13: S14
A14: E10 | B14: Fulfillment - Inventory / Warehouse | C14: Fulfillment Service | D14: B | E14: =COUNTIF('2. Backlog'!$B$2:$B$85,A14) -> 6 | F14: =SUMIFS('2. Backlog'!$G$2:$G$85,'2. Backlog'!$B$2:$B$85,A14) -> 42 | G14: =F14/$F$19 -> 0.06431853 | H14: S4 | I14: S15
A15: E11 | B15: Fulfillment - Shipping & Logistics | C15: Fulfillment Service | D15: A | E15: =COUNTIF('2. Backlog'!$B$2:$B$85,A15) -> 5 | F15: =SUMIFS('2. Backlog'!$G$2:$G$85,'2. Backlog'!$B$2:$B$85,A15) -> 26 | G15: =F15/$F$19 -> 0.039816233 | H15: S14 | I15: S16
A16: E12 | B16: User Reputation | C16: User Service | D16: A | E16: =COUNTIF('2. Backlog'!$B$2:$B$85,A16) -> 3 | F16: =SUMIFS('2. Backlog'!$G$2:$G$85,'2. Backlog'!$B$2:$B$85,A16) -> 14 | G16: =F16/$F$19 -> 0.02143951 | H16: S13 | I16: S16
... A18: E14 | B18: Quality & NFR Compliance | C18: Cross-cutting | D18: QA | E18: =COUNTIF('2. Backlog'!$B$2:$B$85,A18) -> 6 | F18: =SUMIFS('2. Backlog'!$G$2:$G$85,'2. Backlog'!$B$2:$B$85,A18) -> 53 | G18: =F18/$F$19 -> 0.081163859 | H18: S3 | I18: S16
B19: TOTAL | E19: =SUM(E5:E18) -> 84 | F19: =SUM(F5:F18) -> 653

Sheet 4. Sprint Plan
A1: SPRINT PLAN — LOAD VS. CAPACITY BY TRACK
A2: Capacity per sprint at 100%: Track A = 20 · Track B = 16 · Frontend = 8 · QA = 8 dev-day. S8 runs 3 calendar weeks to absorb the 5-day Tet break (06/02/2027); capacity is counted at 80% due to reduced productivity around the break.
A4: Sprint | B4: From | C4: To | D4: Weeks | E4: Capacity | F4: Sprint theme | G4: A load | H4: A cap | I4: B load | J4: B cap | K4: FE load | L4: FE cap | M4: QA load | N4: QA cap | O4: Total load | P4: Total cap | Q4: % used
A5: S0 | B5: 28/09/2026 | C5: 09/10/2026 | D5: 2 | E5: 1 | F5: Tech stack training: Backend (Java, Spring Boot) & Frontend (ReactJS, HTML, CSS) | G5: 20 | H5: =20*$E5 -> 20 | I5: 16 | J5: =16*$E5 -> 16 | K5: 8 | L5: =8*$E5 -> 8 | M5: 0 | N5: =8*$E5 -> 8 | O5: =G5+I5+K5+M5 -> 44 | P5: =H5+J5+L5+N5 -> 52 | Q5: =IFERROR(O5/P5,0) -> 0.84615385
A6: S1 | B6: 12/10/2026 | C6: 23/10/2026 | D6: 2 | E6: 1 | F6: Inception & platform bootstrap | G6: 16 | H6: =20*$E6 -> 20 | I6: 0 | J6: =16*$E6 -> 16 | K6: 0 | L6: =8*$E6 -> 8 | M6: 0 | N6: =8*$E6 -> 8 | O6: =G6+I6+K6+M6 -> 16 | P6: =H6+J6+L6+N6 -> 52 | Q6: =IFERROR(O6/P6,0) -> 0.30769231
A7: S2 | B7: 26/10/2026 | C7: 06/11/2026 | D7: 2 | E7: 1 | F7: Platform: gateway, event bus, environments | G7: 19 | H7: =20*$E7 -> 20 | I7: 0 | J7: =16*$E7 -> 16 | K7: 6 | L7: =8*$E7 -> 8 | M7: 0 | N7: =8*$E7 -> 8 | O7: =G7+I7+K7+M7 -> 25 | P7: =H7+J7+L7+N7 -> 52 | Q7: =IFERROR(O7/P7,0) -> 0.48076923
A8: S3 | B8: 09/11/2026 | C8: 20/11/2026 | D8: 2 | E8: 1 | F8: Platform completion + User Service | G8: 17 | H8: =20*$E8 -> 20 | I8: 15 | J8: =16*$E8 -> 16 | K8: 6 | L8: =8*$E8 -> 8 | M8: 5 | N8: =8*$E8 -> 8 | O8: =G8+I8+K8+M8 -> 43 | P8: =H8+J8+L8+N8 -> 52 | Q8: =IFERROR(O8/P8,0) -> 0.82692308
A9: S4 | B9: 23/11/2026 | C9: 04/12/2026 | D9: 2 | E9: 1 | F9: Authentication & Event log + Inventory record | G9: 16 | H9: =20*$E9 -> 20 | I9: 15 | J9: =16*$E9 -> 16 | K9: 8 | L9: =8*$E9 -> 8 | M9: 5 | N9: =8*$E9 -> 8 | O9: =G9+I9+K9+M9 -> 44 | P9: =H9+J9+L9+N9 -> 52 | Q9: =IFERROR(O9/P9,0) -> 0.84615385
A10: S5 | B10: 07/12/2026 | C10: 18/12/2026 | D10: 2 | E10: 1 | F10: IAM completion + Inventory reservation | G10: 19 | H10: =20*$E10 -> 20 | I10: 16 | J10: =16*$E10 -> 16 | K10: 8 | L10: =8*$E10 -> 8 | M10: 0 | N10: =8*$E10 -> 8 | O10: =G10+I10+K10+M10 -> 43 | P10: =H10+J10+L10+N10 -> 52 | Q10: =IFERROR(O10/P10,0) -> 0.82692308
A11: S6 | B11: 04/01/2027 | C11: 15/01/2027 | D11: 2 | E11: 1 | F11: Catalog + Inventory release + Auction session creation | G11: 19 | H11: =20*$E11 -> 20 | I11: 16 | J11: =16*$E11 -> 16 | K11: 6 | L11: =8*$E11 -> 8 | M11: 0 | N11: =8*$E11 -> 8 | O11: =G11+I11+K11+M11 -> 41 | P11: =H11+J11+L11+N11 -> 52 | Q11: =IFERROR(O11/P11,0) -> 0.78846154
A12: S7 | B12: 18/01/2027 | C12: 29/01/2027 | D12: 2 | E12: 1 | F12: Catalog search + Auction lifecycle + Shopping cart | G12: 17 | H12: =20*$E12 -> 20 | I12: 16 | J12: =16*$E12 -> 16 | K12: 6 | L12: =8*$E12 -> 8 | M12: 0 | N12: =8*$E12 -> 8 | O12: =G12+I12+K12+M12 -> 39 | P12: =H12+J12+L12+N12 -> 52 | Q12: =IFERROR(O12/P12,0) -> 0.75
A13: S8 | B13: 01/02/2027 | C13: 19/02/2027 | D13: 3 | E13: 0.8 | F13: Tet holiday - reduced capacity: Cart & pricing + Auction cancellation | G13: 16 | H13: =20*$E13 -> 16 | I13: 12 | J13: =16*$E13 -> 12.8 | K13: 6 | L13: =8*$E13 -> 6.4 | M13: 0 | N13: =8*$E13 -> 6.4 | O13: =G13+I13+K13+M13 -> 34 | P13: =H13+J13+L13+N13 -> 41.6 | Q13: =IFERROR(O13/P13,0) -> 0.81730769
A14: S9 | B14: 22/02/2027 | C14: 05/03/2027 | D14: 2 | E14: 1 | F14: Checkout + Bidding | G14: 14 | H14: =20*$E14 -> 20 | I14: 12 | J14: =16*$E14 -> 16 | K14: 7 | L14: =8*$E14 -> 8 | M14: 0 | N14: =8*$E14 -> 8 | O14: =G14+I14+K14+M14 -> 33 | P14: =H14+J14+L14+N14 -> 52 | Q14: =IFERROR(O14/P14,0) -> 0.63461538
A15: S10 | B15: 08/03/2027 | C15: 19/03/2027 | D15: 2 | E15: 1 | F15: Stripe payment + Bid concurrency handling | G15: 17 | H15: =20*$E15 -> 20 | I15: 16 | J15: =16*$E15 -> 16 | K15: 8 | L15: =8*$E15 -> 8 | M15: 0 | N15: =8*$E15 -> 8 | O15: =G15+I15+K15+M15 -> 41 | P15: =H15+J15+L15+N15 -> 52 | Q15: =IFERROR(O15/P15,0) -> 0.78846154
A16: S11 | B16: 22/03/2027 | C16: 02/04/2027 | D16: 2 | E16: 1 | F16: Payment webhook + Bid history & anti-sniping + Performance testing | G16: 19 | H16: =20*$E16 -> 20 | I16: 15 | J16: =16*$E16 -> 16 | K16: 8 | L16: =8*$E16 -> 8 | M16: 4 | N16: =8*$E16 -> 8 | O16: =G16+I16+K16+M16 -> 46 | P16: =H16+J16+L16+N16 -> 52 | Q16: =IFERROR(O16/P16,0) -> 0.88461538
... A21: S16 | B21: 31/05/2027 | C21: 11/06/2027 | D21: 2 | E21: 1 | F21: Hardening, performance, pentest, UAT, go-live | G21: 11 | H21: =20*$E21 -> 20 | I21: 0 | J21: =16*$E21 -> 16 | K21: 0 | L21: =8*$E21 -> 8 | M21: 8 | N21: =8*$E21 -> 8 | O21: =G21+I21+K21+M21 -> 19 | P21: =H21+J21+L21+N21 -> 52 | Q21: =IFERROR(O21/P21,0) -> 0.36538462
F22: TOTAL | G22: =SUM(G5:G21) -> 293 | H22: =SUM(H5:H21) -> 336 | I22: =SUM(I5:I21) -> 213 | J22: =SUM(J5:J21) -> 268.8 | K22: =SUM(K5:K21) -> 109 | L22: =SUM(L5:L21) -> 134.4 | M22: =SUM(M5:M21) -> 38 | N22: =SUM(N5:N21) -> 134.4 | ... P22: =SUM(P5:P21) -> 873.6 | Q22: =O22/P22 -> 0.74748168
A23: NOTE: the “Total cap” column includes S16 (the hardening sprint) and all of QA's capacity. The real buffer must be calculated over each track's DELIVERY sprints only — see the table below.
A25: ACTUAL BUFFER BY TRACK (delivery sprints only, EXCLUDING the S16 hardening sprint)
A26: Track | B26: Track name | C26: Delivery sprints | D26: Scope (dev-day) | E26: Capacity (dev-day) | F26: Buffer % | G26: Assessment
A27: A | B27: Track A - Commerce & Platform (Tech Lead 50% + 2 BE) | C27: S1 – S15 | D27: 262 | E27: 296 | F27: =(E27-D27)/E27 -> 0.11486486 | G27: =IF(F27<0.05,"HIGH RISK — add 1 dev",IF(F27<0.15,"Tight — needs scope discipline","Acceptable")) -> Tight — needs scope discipline
A28: B | B28: Track B - Async & Auction (2 BE) | C28: S3 – S15 | D28: 197 | E28: 204.8 | F28: =(E28-D28)/E28 -> 0.038085938 | G28: =IF(F28<0.05,"HIGH RISK — add 1 dev",IF(F28<0.15,"Tight — needs scope discipline","Acceptable")) -> HIGH RISK — add 1 dev
A29: FE | B29: Frontend (1 FE) | C29: S2 – S15 | D29: 101 | E29: 110.4 | F29: =(E29-D29)/E29 -> 0.085144928 | G29: =IF(F29<0.05,"HIGH RISK — add 1 dev",IF(F29<0.15,"Tight — needs scope discipline","Acceptable")) -> Tight — needs scope discipline
A30: QA | B30: QA Automation (1 QA) | C30: S3 – S16 | D30: 38 | E30: 110.4 | F30: =(E30-D30)/E30 -> 0.6557971 | G30: =IF(F30<0.05,"HIGH RISK — add 1 dev",IF(F30<0.15,"Tight — needs scope discipline","Acceptable")) -> Acceptable
A32: Track B (the entire auction flow) is the constraint that governs the pace of the whole plan. Adding 1 backend dev to Track B would raise the buffer from 3.8% to about 22%.

Sheet 5. Milestones
A1: MILESTONES & ACCEPTANCE CRITERIA
A4: Code | B4: Milestone | C4: Date | D4: Sprint | E4: Conditions to declare MET (exit criteria)
A5: M0 | B5: Platform ready | C5: 20/11/2026 | D5: S3 | E5: CI/CD running; event bus can publish/consume; observability has tracing; can deploy to STAGING
A6: M1 | B6: Identity & Catalog | C6: 29/01/2027 | D6: S7 | E6: Sign up / sign in / password reset; product & category CRUD; search <= 800ms; product browsing UI
A7: M2 | B7: Commerce core runs end-to-end | C7: 16/04/2027 | D7: S12 | E7: Cart → checkout → Stripe → order → stock reservation and deduction, running end-to-end on STAGING
A8: M3 | B8: Auction runs end-to-end | C8: 14/05/2027 | D8: S14 | E8: Session creation → concurrent bidding → anti-sniping → settlement → order created from the auction
A9: M4 | B9: Feature complete / code freeze | C9: 28/05/2027 | D9: S15 | E9: GHN waybill; email notifications; reputation-based blocking; all Must-scope done
A10: M5 | B10: Go-Live | C10: 12/06/2027 | D10: S16 | E10: Performance tests meet SRS section 5.1 SLAs; no open High/Critical findings; DR drill passed; UAT signed off
A13: No milestone is scheduled during S8 (Tet, 06/02/2027) or in any sprint running below 100% capacity.

Sheet 6. Deferred
A1: DEFERRED SCOPE — AND WHY
A2: Every item below is in SRS v1.0 but is NOT part of Release 1. The Product Owner needs to sign off on this list.
A4: Code | B4: Item | C4: SRS ref | D4: Reason deferred | E4: Estimate (dev-day) | F4: Release
A5: D01 | B5: Promotions / discount code engine | C5: Section 1.2 (in scope) but MISSING a spec in section 3 | D5: SRS has no spec yet, so it cannot be reliably estimated | E5: 12 | F5: R1.1
A6: D02 | B6: Warehouse selection + multi-warehouse order splitting | C6: 3.6.1 | D6: SRS sets FEATURE_MULTI_WAREHOUSE_ENABLED = false; MVP uses a single warehouse | E6: 16 | F6: R1.1
A7: D03 | B7: Second carrier (GHTK) + multi-carrier strategy | C7: 3.6.2 | D7: 1 carrier is enough for MVP; the adapter framework is already in place | E7: 20 | F7: R1.1
A8: D04 | B8: Push notification channel | C8: 3.2.3 | D8: R1 uses in-app WebSocket for realtime needs | E8: 8 | F8: R1.1
A9: D05 | B9: SMS notification channel | C9: 3.2.3 | D9: SRS sets SMS_NOTIFICATION_ENABLED = false | E9: 6 | F9: R2
A10: D06 | B10: Migrate to OpenSearch + relevance tuning | C10: 3.3.3 | D10: Postgres FTS is sufficient under 500,000 products | E10: 14 | F10: R1.1
A11: D07 | B11: Product discovery (popularity, ending soon, recommendations) | C11: 3.3.3 | D11: Not part of the core transaction flow | E11: 12 | F11: R1.1
A12: D08 | B12: PDF invoice / receipt generation | C12: 3.4.3 | D12: R1 sends an HTML email receipt | E12: 10 | F12: R1.1
A13: D09 | B13: Dynamic role/privilege CRUD (admin-defined roles) | C13: 3.1.1 | D13: R1 uses the fixed RBAC matrix from section 2.7 | E13: 10 | F13: R1.1
A14: D10 | B14: Full violation-handling & penalty engine | C14: 3.1.2 | D14: R1 only deducts points for late payment + manual admin adjustment | E14: 8 | F14: R1.1
A15: D11 | B15: Dispute handling & review flagging | C15: 3.1.2 | D15: Requires a dispute workflow definition (missing from the SRS) | E15: 10 | F15: R2
A16: D12 | B16: Dedicated console for Support Staff | C16: 2.3 / 2.7 | D16: R1: Support uses the Admin console | E16: 12 | F16: R1.1
... A26: D22 | B26: In-house logistics system | C26: 1.2 (out of scope for v1.0) | D26: SRS already declares this out of scope for v1.0 | E26: 0 | F26: R2
B27: TOTAL | E27: =SUM(E5:E26) -> 207

Sheet 7. Risks
A1: RISK REGISTER
A2: Score = Probability x Impact (1-5 scale), sorted descending. Risks scoring 20 or above are reviewed every sprint.
A4: Code | B4: Risk | C4: Category | D4: Probability | E4: Impact | F4: Score | G4: Mitigation | H4: Owner
A5: R01 | B5: Capacity shortfall: R1 scope is 609 dev-day against a 6-month / 8-person target | C5: Schedule | D5: High | E5: High | F5: 25 | G5: Decide on one of three options before 30/09/2026: (A) add 3 backend devs to hold the 16/04/2027 date; (B) keep the 8-person team, go-live 12/06/2027; (C) cut auction to R2, go-live 30/04/2027 | H5: PO/PM + Sponsor
A6: R02 | B6: Only 1 frontend dev for 4 UI surfaces (buyer, seller, admin, realtime bidding) | C6: Schedule | D6: High | E6: High | F6: 20 | G6: Use a ready-made admin template (Ant Design Pro / Refine) for admin and seller; no custom design in R1; add 1 more FE from S7 if FE velocity drops below 80% | H6: Tech Lead
A7: R03 | B7: Bid concurrency handling: 3,000 bids/minute, latency <= 300ms, zero lost bids | C7: Technical | D7: High | E7: High | F7: 20 | G7: Spike Redis + optimistic locking in S6 (before real coding in S10); performance test in S11-S12, NOT waiting until S16; split Auction into its own service from day one | H7: Tech Lead
A8: R04 | B8: 7 microservices with 5 devs is roughly 1 dev/service (an anti-pattern), operational overhead too high | C8: Technical | D8: High | E8: Medium | F8: 15 | G8: ADR-002: modular monolith with bounded contexts + separate schemas + event bus, EXCEPT Auction Service, which is split out (due to the 3,000 bids/minute NFR). Split further only when scaling is truly needed | H8: Tech Lead + PO
A9: R05 | B9: SRS gaps remain: missing System Context / Architecture / Component diagrams; promotions are in scope but unspecified; dispute workflow and Support Staff role are missing | C9: Requirements | D9: High | E9: Medium | F9: 15 | G9: BA completes SRS v1.1 before S4 (04/12/2026); promotions move to R1.1; disputes move to R2. PO signs off on the gap list | H9: PO + BA (HauNK)
A10: R06 | B10: Tet 2027 (06/02) plus Christmas and New Year cost roughly 2.5 weeks of capacity | C10: Calendar | D10: High | E10: Medium | F10: 15 | G10: Already built into the plan: S8 runs 3 weeks at 80% capacity; the 19/12-03/01 break is not counted as a sprint; no milestone is scheduled in S8 | H10: PM
A11: R10 | B11: Key-person dependency: each domain is owned by just 1 dev | C11: People | D11: High | E11: Medium | F11: 15 | G11: Require 2 reviewers per PR; rotate pairing once per sprint; ADRs and OpenAPI stay living documents; no long leave during a milestone sprint | H11: PM + Tech Lead
A12: R11 | B12: Scope creep from mid-cycle stakeholder requests | C12: Schedule | D12: High | E12: Medium | F12: 15 | G12: Change control: every new request must trade 1-for-1 against an existing Must item; only the PO can add work to the sprint backlog | H12: PO
A13: R07 | B13: Strong consistency requirement (orders / payment / auction) on an event-driven architecture | C13: Technical | D13: Medium | E13: High | F13: 12 | G13: ADR-003: Saga + Transactional Outbox + idempotency keys on every critical API; contract tests are mandatory in CI | H13: Tech Lead
A14: R08 | B14: Stripe integration and PCI-DSS compliance | C14: Compliance | D14: Medium | E14: High | F14: 12 | G14: Use Stripe Elements/Checkout so card data never touches our systems; PCI-DSS SAQ-A checklist from S10; pentest in S16 | H14: Tech Lead + QA
A15: R09 | B15: Quality and readiness of the GHN sandbox / carrier API | C15: External | D15: Medium | E15: Medium | F15: 9 | G15: Request sandbox access from S11 (before coding in S15); mock adapter + contract tests to avoid being blocked; fallback is manual waybill creation | H15: Tech Lead
A16: R12 | B16: Unit test coverage >= 70% (NFR 5.6) sacrificed under deadline pressure | C16: Quality | D16: Medium | E16: Medium | F16: 9 | G16: CI coverage gate blocks merges from S3; DoD requires tests; no exceptions - technical debt is tracked as a defect | H16: QA + Tech Lead

Sheet 8. Team & Process
A1: TEAM, CAPACITY & WORKING PROCESS
A4: A. TEAM CONFIGURATION (8 people)
A5: Role | B5: Count | C5: Dev FTE | D5: Assignment | E5: Key responsibilities
A6: Product Owner / Project Manager | B6: 1 | C6: 0 | D6: Both tracks - Tuan | E6: Owns the backlog and its priority order; the ONLY person allowed to add work to the sprint backlog; runs change control; reports to stakeholders; signs off on the deferred list
A7: Tech Lead / Solution Architect | B7: 1 | C7: 0.5 | D7: Track A (plus ADR ownership, reviews both tracks) | E7: Owns ADRs and contracts (OpenAPI + event schema); reviews 100% of PRs on critical flows; runs technical spikes; accountable for meeting the NFRs in SRS section 5
A8: Backend Developer | B8: 4 | C8: 4 | D8: 2 on Track A, 2 on Track B | E8: Writes code with unit and integration tests per the DoD; 2 on Track A (platform and commerce), 2 on Track B (auction and inventory); rotates pairing once per sprint
A9: Frontend Developer | B9: 1 | C9: 1 | D9: Shared | E9: Buyer web, admin and seller portal (using templates), realtime bidding UI; owns the design system and accessibility
A10: QA / Automation Engineer | B10: 1 | C10: 0 | D10: Shared (capacity tracked separately) | E10: Test strategy; automation framework, contract tests and E2E; performance testing; owns the CI quality gate
A11: TOTAL | B11: =SUM(B6:B10) -> 8 | C11: =SUM(C6:C10) -> 5.5
A14: B. DEFINITION OF READY — not met means it does NOT go into a sprint
A15: • Has a clear problem statement and user value: who, does what, to get what
A16: • Acceptance criteria written as Given-When-Then, and measurable
A17: • API contract (OpenAPI) and event schema agreed with dependent services
A18: • Dependencies identified, and each is either done or has a mock/stub available
A19: • Estimate is no more than 10 dev-day (larger items must be split — a story can't span sprints)
A20: • Has a wireframe if there's a UI change
A21: • Clearly identifies which SRS section 2.6 configuration is affected and what its default value is
A24: C. DEFINITION OF DONE — not met means it does NOT count as finished
A25: • Code merged to main; approved by 2 reviewers (mandatory for critical flows: payment, orders, bidding, settlement)
A26: • Unit test coverage >= 70% for the changed module — a CI quality gate blocks merges (NFR section 5.6)
A27: • Contract tests pass; OpenAPI spec updated and auto-published
... A36: D. CADENCE
A37: Activity | B37: Frequency | C37: Duration | D37: Attendees | E37: Output
A38: Daily standup | B38: Daily, 9:15 | C38: 15 min | D38: Whole team | E38: Blockers are named and someone owns unblocking them that day
A39: Sprint planning | B39: Monday of each sprint | C39: 2 hours | D39: Whole team | E39: Sprint goal and sprint backlog committed
A40: Backlog refinement | B40: Wednesday of week 1 | C40: 90 min | D40: PO, Tech Lead, 1 dev per track, QA | E40: Next sprint's features reach Definition of Ready
A41: Sprint review / demo | B41: Thursday, end of sprint | C41: 60 min | D41: Whole team + stakeholders | E41: Demo on STAGING (never on a dev machine)
A42: Retrospective | B42: Thursday, end of sprint | C42: 60 min | D42: Whole team | E42: At most 2 action items, each with an owner and a deadline
A43: Architecture review | B43: Every 2 sprints | C43: 90 min | D43: Tech Lead + Backend + PO | E43: New ADR or an amendment to an existing one
A44: Risk review | B44: Every sprint | C44: 30 min | D44: PM, Tech Lead, PO | E44: Risk register updated; risks scoring 20+ get a new action
A45: Milestone gate | B45: Per sheet 5 | C45: 2 hours | D45: Whole team + Sponsor | E45: GO / NO-GO decision based on exit criteria
A48: E. METRICS TRACKED EVERY SPRINT
A49: • Velocity (dev-day completed) versus commitment — flag if below 85% for 2 consecutive sprints
A50: • Scope added / removed within a sprint (target is zero — every change must be a 1-for-1 trade-off)
A51: • Defect leakage rate from STAGING to UAT
A52: • Unit test coverage and contract test count (may only increase, never decrease)
A53: • Number of ADRs still “proposed” for more than 1 sprint (architecture debt)
A54: • R1 scope burn-down: dev-day remaining versus sprints remaining
